pyguitemp/__init__.py
pyguitemp/__main__.py
pyguitemp/config.py
pyguitemp/core.py
pyguitemp/logging.py
pyguitemp/plugins.py
pyguitemp/scripts.py
pyguitemp/threads.py
pyguitemp/extensions/__init__.py
pyguitemp/extensions/about_dialog/__init__.py
pyguitemp/extensions/about_dialog/about_dialog.py
pyguitemp/extensions/about_dialog/description
pyguitemp/extensions/about_dialog/licence
pyguitemp/extensions/about_dialog/license
pyguitemp/extensions/about_dialog/logo.png
pyguitemp/extensions/example_plugin/__init__.py
pyguitemp/extensions/example_plugin/central.py
pyguitemp/extensions/example_plugin/menu.py
pyguitemp/extensions/example_plugin/notebook.py
pyguitemp/extensions/example_plugin/tools.py
pyguitemp/extensions/load_data/MOCK_DATA.csv
pyguitemp/extensions/load_data/__init__.py
pyguitemp/extensions/load_data/model.py
pyguitemp/extensions/load_data/presenter.py
pyguitemp/extensions/load_data/view.py
pyguitemp/skeleton/__init__.py
pyguitemp/skeleton/__main__.py
pyguitemp/skeleton/config.py
pyguitemp/skeleton/extensions/__init__.py
tests/__init__.py
tests/conftest.py
tests/test_core.py
tests/test_logging.py
tests/test_plugins.py
tests/test_scripts.py
tests/test_threads.py
pyguitemp-0.1.21.dist-info/LICENSE
pyguitemp-0.1.21.dist-info/METADATA
pyguitemp-0.1.21.dist-info/WHEEL
pyguitemp-0.1.21.dist-info/top_level.txt
pyguitemp-0.1.21.dist-info/RECORD
